files/linker
files/linker.py
linker_bookmarks-0.0.2.data/scripts/linker
linker_bookmarks-0.0.2.data/scripts/linker.py
linker_bookmarks-0.0.2.dist-info/LICENSE.md
linker_bookmarks-0.0.2.dist-info/METADATA
linker_bookmarks-0.0.2.dist-info/WHEEL
linker_bookmarks-0.0.2.dist-info/top_level.txt
linker_bookmarks-0.0.2.dist-info/RECORD
