Metadata-Version: 2.1
Name: linker-bookmarks
Version: 0.0.2
Summary: linker: cli based bookmark manager.
Home-page: https://github.com/monotone-the-musical/linker
Author: mtm
Author-email: MTM <monotone.the.musical@gmail.com>
Project-URL: Homepage, https://github.com/monotone-the-musical/linker
Project-URL: Bug Tracker, https://github.com/monotone-the-musical/linker/issues
Classifier: Programming Language :: Python :: 3
Classifier: License :: OSI Approved :: MIT License
Classifier: Operating System :: POSIX :: Linux
License-File: LICENSE.md
Requires-Dist: pick
Requires-Dist: configparser
Requires-Dist: iterfzf
Requires-Dist: pyperclip
Requires-Dist: python-dateutil
